gltf_builder/__init__.py
gltf_builder/accessor.py
gltf_builder/asset.py
gltf_builder/buffer.py
gltf_builder/builder.py
gltf_builder/element.py
gltf_builder/geometries.py
gltf_builder/holder.py
gltf_builder/mesh.py
gltf_builder/node.py
gltf_builder/primitives.py
gltf_builder/py.typed
gltf_builder/quaternion.md
gltf_builder/quaternion.py
gltf_builder/view.py
gltf_builder-0.1.8.dist-info/METADATA
gltf_builder-0.1.8.dist-info/WHEEL
gltf_builder-0.1.8.dist-info/licenses/LICENSE
gltf_builder-0.1.8.dist-info/RECORD
