Metadata-Version: 2.4
Name: gltf-builder
Version: 0.1.8
Summary: Library for building gltf files, handling buffers, views, and accessors.
Author-email: Bob Kerns <1154903+BobKerns@users.noreply.github.com>
License-File: LICENSE
Classifier: Development Status :: 4 - Beta
Classifier: Environment :: GPU
Classifier: Environment :: Web Environment
Classifier: Intended Audience :: Developers
Classifier: License :: OSI Approved :: MIT License
Classifier: Operating System :: OS Independent
Classifier: Programming Language :: Python :: 3.11
Classifier: Topic :: File Formats
Classifier: Topic :: Multimedia :: Graphics
Classifier: Typing :: Typed
Requires-Python: >=3.11
Requires-Dist: numpy>=2.0.0
Requires-Dist: pygltflib>=1.16.3
